{
    "levelConfiguration": {
        "skin": "Standard",
        "cellWidth": 1.5,
        "cellHeight": 1.0,
        "spawnTriggerRoomLocation": 0.9,
        "roomsToSpawnAtOnce": 1,
        "roomCellsWide": 16,
        "roomCellsTall": 12
    },
    "zones": [
        {
            "name": "Outside",
            "lengthInCells": 4,
            "spriteSetPrefix": "Outside",
			"needsCeiling": false,
			"backgroundMusic": "Music/BEAST1-BGM-PatternsInRhyme",
            "intelSpawnPercentage": 0.2,
            "roomConfiguration": {
                "floorHeightChangeProbability": 0.3,
                "enemySpawnProbability": 0.5,
            }
        },
        {
            "name": "SecurityCheckpoint",
            "lengthInCells": 12,
            "spriteSetPrefix": "SecurityCheckpoint1",
            "needsCeiling": true,
			"backgroundMusic": "Music/BEAST1-BGM-PatternsInRhyme",
            "intelSpawnPercentage": 0.2,
            "roomConfiguration": {
                "floorHeightChangeProbability": 0.25,
                "enemySpawnProbability": 0.5
            }
        },
    ]
}